{
  "summary": {
    "paper_bankroll_start": 1000.0,
    "paper_bankroll_current": 1000.53,
    "paper_pnl": 0.53,
    "paper_pnl_pct": 0.05,
    "total_paper_trades": 70,
    "kalshi_open_positions": 0,
    "paper_win_rate": 7.1,
    "paper_wins": 5,
    "paper_losses": 65,
    "kalshi_balance": 500.6,
    "polymarket_balance": 520.0,
    "poly_paper_bankroll": 500.0,
    "poly_paper_trades": 6,
    "poly_paper_pnl": 0,
    "total_trades": 76
  },
  "paper_trades": [
    {
      "id": 9,
      "ticker": "will-nyc-have-between-3-and-4-inches-of-precipitation-in-march",
      "side": "yes",
      "entry_price": 0.185,
      "contracts": 50.0,
      "model_prob": 1.0,
      "edge": 0.815,
      "entered_at": "2026-03-22 20:55:38",
      "result": null,
      "pnl": null,
      "resolved_at": null,
      "platform": "polymarket",
      "description": "Will NYC have between 3 and 4 inches of precipitation in March?"
    },
    {
      "id": 10,
      "ticker": "will-nyc-have-between-4-and-5-inches-of-precipitation-in-march",
      "side": "yes",
      "entry_price": 0.34,
      "contracts": 50.0,
      "model_prob": 1.0,
      "edge": 0.66,
      "entered_at": "2026-03-22 20:55:38",
      "result": null,
      "pnl": null,
      "resolved_at": null,
      "platform": "polymarket",
      "description": "Will NYC have between 4 and 5 inches of precipitation in March?"
    },
    {
      "id": 11,
      "ticker": "will-nyc-have-between-5-and-6-inches-of-precipitation-in-march",
      "side": "no",
      "entry_price": 0.755,
      "contracts": 50.0,
      "model_prob": 0.1329,
      "edge": 0.1121,
      "entered_at": "2026-03-22 20:55:38",
      "result": null,
      "pnl": null,
      "resolved_at": null,
      "platform": "polymarket",
      "description": "Will NYC have between 5 and 6 inches of precipitation in March?"
    },
    {
      "id": 12,
      "ticker": "will-seattle-have-between-4-and-5-inches-of-precipitation-in-march",
      "side": "yes",
      "entry_price": 0.177,
      "contracts": 50.0,
      "model_prob": 1.0,
      "edge": 0.823,
      "entered_at": "2026-03-22 20:55:38",
      "result": null,
      "pnl": null,
      "resolved_at": null,
      "platform": "polymarket",
      "description": "Will Seattle have between 4 and 5 inches of precipitation in March?"
    },
    {
      "id": 13,
      "ticker": "will-seattle-have-between-5-and-6-inches-of-precipitation-in-march",
      "side": "yes",
      "entry_price": 0.7145,
      "contracts": 50.0,
      "model_prob": 1.0,
      "edge": 0.2855,
      "entered_at": "2026-03-22 20:55:38",
      "result": null,
      "pnl": null,
      "resolved_at": null,
      "platform": "polymarket",
      "description": "Will Seattle have between 5 and 6 inches of precipitation in March?"
    },
    {
      "id": 14,
      "ticker": "will-seattle-have-between-6-and-7-inches-of-precipitation-in-march",
      "side": "yes",
      "entry_price": 0.0415,
      "contracts": 50.0,
      "model_prob": 1.0,
      "edge": 0.9585,
      "entered_at": "2026-03-22 20:55:38",
      "result": null,
      "pnl": null,
      "resolved_at": null,
      "platform": "polymarket",
      "description": "Will Seattle have between 6 and 7 inches of precipitation in March?"
    },
    {
      "id": 125,
      "ticker": "KXHIGHTHOU-26MAR21-B87.5",
      "side": "yes",
      "entry_price": 0.01,
      "contracts": 1,
      "model_prob": 0.3333333333333333,
      "edge": 0.3133333333333333,
      "entered_at": "2026-03-21 23:06:51",
      "result": "loss",
      "pnl": -0.01,
      "resolved_at": "2026-03-22 13:10:00",
      "platform": "kalshi",
      "description": "Will the maximum temperature be  87-88\u00b0 on Mar 21, 2026?"
    },
    {
      "id": 124,
      "ticker": "KXHIGHTHOU-26MAR21-T87",
      "side": "yes",
      "entry_price": 0.9,
      "contracts": 1,
      "model_prob": 1.0,
      "edge": 0.08999999999999998,
      "entered_at": "2026-03-21 21:10:33",
      "result": "win",
      "pnl": 0.09999999999999998,
      "resolved_at": "2026-03-22 13:09:58",
      "platform": "kalshi",
      "description": "Will the maximum temperature be  <87\u00b0 on Mar 21, 2026?"
    },
    {
      "id": 122,
      "ticker": "KXLOWTNYC-26MAR21-T48",
      "side": "yes",
      "entry_price": 0.24,
      "contracts": 1,
      "model_prob": 0.3333333333333333,
      "edge": 0.07333333333333332,
      "entered_at": "2026-03-21 21:05:01",
      "result": "loss",
      "pnl": -0.24,
      "resolved_at": "2026-03-22 13:10:00",
      "platform": "kalshi",
      "description": "Will the minimum temperature be  >48\u00b0 on Mar 21, 2026?"
    },
    {
      "id": 123,
      "ticker": "KXHIGHAUS-26MAR21-B91.5",
      "side": "yes",
      "entry_price": 0.24,
      "contracts": 1,
      "model_prob": 0.3333333333333333,
      "edge": 0.07333333333333332,
      "entered_at": "2026-03-21 21:05:01",
      "result": "loss",
      "pnl": -0.24,
      "resolved_at": "2026-03-22 13:09:57",
      "platform": "kalshi",
      "description": "Will the **high temp in Austin** be 91-92\u00b0 on Mar 21, 2026?"
    },
    {
      "id": 111,
      "ticker": "KXHIGHTPHX-26MAR21-B103.5",
      "side": "yes",
      "entry_price": 0.37,
      "contracts": 1,
      "model_prob": 0.6666666666666666,
      "edge": 0.2766666666666666,
      "entered_at": "2026-03-21 20:36:50",
      "result": "loss",
      "pnl": -0.37,
      "resolved_at": "2026-03-22 13:10:15",
      "platform": "kalshi",
      "description": "Will the maximum temperature be  103-104\u00b0 on Mar 21, 2026?"
    },
    {
      "id": 113,
      "ticker": "KXHIGHTSEA-26MAR21-B48.5",
      "side": "yes",
      "entry_price": 0.24,
      "contracts": 1,
      "model_prob": 0.3333333333333333,
      "edge": 0.07333333333333332,
      "entered_at": "2026-03-21 20:36:50",
      "result": "loss",
      "pnl": -0.24,
      "resolved_at": "2026-03-22 13:10:08",
      "platform": "kalshi",
      "description": "Will the maximum temperature be  48-49\u00b0 on Mar 21, 2026?"
    },
    {
      "id": 114,
      "ticker": "KXHIGHDEN-26MAR21-B86.5",
      "side": "yes",
      "entry_price": 0.25,
      "contracts": 1,
      "model_prob": 0.3333333333333333,
      "edge": 0.06333333333333331,
      "entered_at": "2026-03-21 20:36:50",
      "result": "win",
      "pnl": 0.75,
      "resolved_at": "2026-03-22 11:10:01",
      "platform": "kalshi",
      "description": "Will the **high temp in Denver** be 86-87\u00b0 on Mar 21, 2026?"
    },
    {
      "id": 115,
      "ticker": "KXLOWTDEN-26MAR21-B48.5",
      "side": "yes",
      "entry_price": 0.01,
      "contracts": 1,
      "model_prob": 0.07913669064748201,
      "edge": 0.05913669064748201,
      "entered_at": "2026-03-21 20:36:50",
      "result": "loss",
      "pnl": -0.01,
      "resolved_at": "2026-03-22 13:09:35",
      "platform": "kalshi",
      "description": "Will the minimum temperature be  48-49\u00b0 on Mar 21, 2026?"
    },
    {
      "id": 116,
      "ticker": "KXHIGHMIA-26MAR21-T75",
      "side": "yes",
      "entry_price": 0.01,
      "contracts": 1,
      "model_prob": 0.07692307692307693,
      "edge": 0.05692307692307693,
      "entered_at": "2026-03-21 20:36:50",
      "result": "loss",
      "pnl": -0.01,
      "resolved_at": "2026-03-22 13:09:49",
      "platform": "kalshi",
      "description": "Will the **high temp in Miami** be <75\u00b0 on Mar 21, 2026?"
    },
    {
      "id": 118,
      "ticker": "KXHIGHTSFO-26MAR21-T73",
      "side": "yes",
      "entry_price": 0.46,
      "contracts": 1,
      "model_prob": 0.5323741007194245,
      "edge": 0.05237410071942446,
      "entered_at": "2026-03-21 20:36:50",
      "result": "win",
      "pnl": 0.54,
      "resolved_at": "2026-03-22 13:10:15",
      "platform": "kalshi",
      "description": "Will the maximum temperature be  >73\u00b0 on Mar 21, 2026?"
    },
    {
      "id": 119,
      "ticker": "KXHIGHNY-26MAR21-B53.5",
      "side": "yes",
      "entry_price": 0.01,
      "contracts": 1,
      "model_prob": 0.07194244604316546,
      "edge": 0.05194244604316546,
      "entered_at": "2026-03-21 20:36:50",
      "result": "loss",
      "pnl": -0.01,
      "resolved_at": "2026-03-22 13:09:29",
      "platform": "kalshi",
      "description": "Will the **high temp in NYC** be 53-54\u00b0 on Mar 21, 2026?"
    },
    {
      "id": 120,
      "ticker": "KXLOWTMIA-26MAR21-B57.5",
      "side": "yes",
      "entry_price": 0.01,
      "contracts": 1,
      "model_prob": 0.07100591715976332,
      "edge": 0.05100591715976331,
      "entered_at": "2026-03-21 20:36:50",
      "result": "loss",
      "pnl": -0.01,
      "resolved_at": "2026-03-22 18:34:42",
      "platform": "kalshi",
      "description": "Will the minimum temperature be  57-58\u00b0 on Mar 21, 2026?"
    },
    {
      "id": 102,
      "ticker": "KXHIGHTMIN-26MAR21-T79",
      "side": "yes",
      "entry_price": 0.19,
      "contracts": 1,
      "model_prob": 0.3333333333333333,
      "edge": 0.12333333333333331,
      "entered_at": "2026-03-21 20:28:45",
      "result": "loss",
      "pnl": -0.19,
      "resolved_at": "2026-03-22 13:09:53",
      "platform": "kalshi",
      "description": "Will the maximum temperature be  >79\u00b0 on Mar 21, 2026?"
    },
    {
      "id": 103,
      "ticker": "KXHIGHTMIN-26MAR21-B76.5",
      "side": "yes",
      "entry_price": 0.01,
      "contracts": 1,
      "model_prob": 0.10650887573964497,
      "edge": 0.08650887573964498,
      "entered_at": "2026-03-21 20:28:45",
      "result": "loss",
      "pnl": -0.01,
      "resolved_at": "2026-03-22 13:09:54",
      "platform": "kalshi",
      "description": "Will the maximum temperature be  76-77\u00b0 on Mar 21, 2026?"
    },
    {
      "id": 106,
      "ticker": "KXHIGHCHI-26MAR21-B69.5",
      "side": "yes",
      "entry_price": 0.01,
      "contracts": 1,
      "model_prob": 0.09467455621301775,
      "edge": 0.07467455621301776,
      "entered_at": "2026-03-21 20:28:45",
      "result": "loss",
      "pnl": -0.01,
      "resolved_at": "2026-03-22 13:09:47",
      "platform": "kalshi",
      "description": "Will the high temp in Chicago be 69-70\u00b0 on Mar 21, 2026?"
    },
    {
      "id": 110,
      "ticker": "KXHIGHTMIN-26MAR21-B76.5",
      "side": "yes",
      "entry_price": 0.05,
      "contracts": 1,
      "model_prob": 0.12949640287769784,
      "edge": 0.06949640287769784,
      "entered_at": "2026-03-21 20:28:45",
      "result": "loss",
      "pnl": -0.05,
      "resolved_at": "2026-03-22 13:09:54",
      "platform": "kalshi",
      "description": "Will the maximum temperature be  76-77\u00b0 on Mar 21, 2026?"
    },
    {
      "id": 91,
      "ticker": "KXHIGHTDC-26MAR21-B63.5",
      "side": "yes",
      "entry_price": 0.01,
      "contracts": 1,
      "model_prob": 0.12949640287769784,
      "edge": 0.10949640287769785,
      "entered_at": "2026-03-21 19:56:46",
      "result": "loss",
      "pnl": -0.01,
      "resolved_at": "2026-03-22 13:09:52",
      "platform": "kalshi",
      "description": "Will the maximum temperature be  63-64\u00b0 on Mar 21, 2026?"
    },
    {
      "id": 95,
      "ticker": "KXHIGHTDAL-26MAR21-B90.5",
      "side": "yes",
      "entry_price": 0.22,
      "contracts": 1,
      "model_prob": 0.3333333333333333,
      "edge": 0.09333333333333331,
      "entered_at": "2026-03-21 19:56:46",
      "result": "win",
      "pnl": 0.78,
      "resolved_at": "2026-03-22 13:09:44",
      "platform": "kalshi",
      "description": "Will the maximum temperature be  90-91\u00b0 on Mar 21, 2026?"
    },
    {
      "id": 96,
      "ticker": "KXLOWTNYC-26MAR21-T41",
      "side": "yes",
      "entry_price": 0.03,
      "contracts": 1,
      "model_prob": 0.12949640287769784,
      "edge": 0.08949640287769785,
      "entered_at": "2026-03-21 19:56:46",
      "result": "loss",
      "pnl": -0.03,
      "resolved_at": "2026-03-22 13:10:00",
      "platform": "kalshi",
      "description": "Will the minimum temperature be  <41\u00b0 on Mar 21, 2026?"
    },
    {
      "id": 97,
      "ticker": "KXHIGHLAX-26MAR21-B78.5",
      "side": "yes",
      "entry_price": 0.02,
      "contracts": 1,
      "model_prob": 0.11834319526627218,
      "edge": 0.08834319526627218,
      "entered_at": "2026-03-21 19:56:46",
      "result": "loss",
      "pnl": -0.02,
      "resolved_at": "2026-03-22 13:10:10",
      "platform": "kalshi",
      "description": "Will the **high temp in LA** be 78-79\u00b0 on Mar 21, 2026?"
    },
    {
      "id": 98,
      "ticker": "KXHIGHTDC-26MAR21-B63.5",
      "side": "yes",
      "entry_price": 0.01,
      "contracts": 1,
      "model_prob": 0.10650887573964497,
      "edge": 0.08650887573964498,
      "entered_at": "2026-03-21 19:56:46",
      "result": "loss",
      "pnl": -0.01,
      "resolved_at": "2026-03-22 13:09:52",
      "platform": "kalshi",
      "description": "Will the maximum temperature be  63-64\u00b0 on Mar 21, 2026?"
    },
    {
      "id": 99,
      "ticker": "KXHIGHTDAL-26MAR21-B90.5",
      "side": "yes",
      "entry_price": 0.23,
      "contracts": 1,
      "model_prob": 0.3333333333333333,
      "edge": 0.0833333333333333,
      "entered_at": "2026-03-21 19:56:46",
      "result": "win",
      "pnl": 0.77,
      "resolved_at": "2026-03-22 13:09:44",
      "platform": "kalshi",
      "description": "Will the maximum temperature be  90-91\u00b0 on Mar 21, 2026?"
    },
    {
      "id": 100,
      "ticker": "KXHIGHLAX-26MAR21-B78.5",
      "side": "yes",
      "entry_price": 0.03,
      "contracts": 1,
      "model_prob": 0.11834319526627218,
      "edge": 0.07834319526627219,
      "entered_at": "2026-03-21 19:56:46",
      "result": "loss",
      "pnl": -0.03,
      "resolved_at": "2026-03-22 13:10:10",
      "platform": "kalshi",
      "description": "Will the **high temp in LA** be 78-79\u00b0 on Mar 21, 2026?"
    },
    {
      "id": 81,
      "ticker": "KXHIGHMIA-26MAR21-B79.5",
      "side": "yes",
      "entry_price": 0.06,
      "contracts": 1,
      "model_prob": 0.3333333333333333,
      "edge": 0.2633333333333333,
      "entered_at": "2026-03-21 19:55:50",
      "result": "loss",
      "pnl": -0.06,
      "resolved_at": "2026-03-22 13:09:50",
      "platform": "kalshi",
      "description": "Will the **high temp in Miami** be 79-80\u00b0 on Mar 21, 2026?"
    },
    {
      "id": 82,
      "ticker": "KXHIGHMIA-26MAR21-B79.5",
      "side": "yes",
      "entry_price": 0.13,
      "contracts": 1,
      "model_prob": 0.3333333333333333,
      "edge": 0.1933333333333333,
      "entered_at": "2026-03-21 19:55:50",
      "result": "loss",
      "pnl": -0.13,
      "resolved_at": "2026-03-22 13:09:50",
      "platform": "kalshi",
      "description": "Will the **high temp in Miami** be 79-80\u00b0 on Mar 21, 2026?"
    },
    {
      "id": 83,
      "ticker": "KXHIGHMIA-26MAR21-B75.5",
      "side": "yes",
      "entry_price": 0.01,
      "contracts": 1,
      "model_prob": 0.17159763313609466,
      "edge": 0.15159763313609464,
      "entered_at": "2026-03-21 19:55:50",
      "result": "loss",
      "pnl": -0.01,
      "resolved_at": "2026-03-22 13:09:50",
      "platform": "kalshi",
      "description": "Will the **high temp in Miami** be 75-76\u00b0 on Mar 21, 2026?"
    },
    {
      "id": 85,
      "ticker": "KXHIGHTDC-26MAR21-B67.5",
      "side": "yes",
      "entry_price": 0.01,
      "contracts": 1,
      "model_prob": 0.14388489208633093,
      "edge": 0.12388489208633092,
      "entered_at": "2026-03-21 19:55:50",
      "result": "loss",
      "pnl": -0.01,
      "resolved_at": "2026-03-22 13:09:52",
      "platform": "kalshi",
      "description": "Will the maximum temperature be  67-68\u00b0 on Mar 21, 2026?"
    },
    {
      "id": 86,
      "ticker": "KXLOWTCHI-26MAR21-B37.5",
      "side": "yes",
      "entry_price": 0.01,
      "contracts": 1,
      "model_prob": 0.1366906474820144,
      "edge": 0.1166906474820144,
      "entered_at": "2026-03-21 19:55:50",
      "result": "loss",
      "pnl": -0.01,
      "resolved_at": "2026-03-22 13:09:30",
      "platform": "kalshi",
      "description": "Will the minimum temperature be  37-38\u00b0 on Mar 21, 2026?"
    },
    {
      "id": 87,
      "ticker": "KXHIGHMIA-26MAR21-B75.5",
      "side": "yes",
      "entry_price": 0.01,
      "contracts": 1,
      "model_prob": 0.1366906474820144,
      "edge": 0.1166906474820144,
      "entered_at": "2026-03-21 19:55:50",
      "result": "loss",
      "pnl": -0.01,
      "resolved_at": "2026-03-22 13:09:50",
      "platform": "kalshi",
      "description": "Will the **high temp in Miami** be 75-76\u00b0 on Mar 21, 2026?"
    },
    {
      "id": 74,
      "ticker": "KXHIGHTSEA-26MAR21-T46",
      "side": "yes",
      "entry_price": 0.01,
      "contracts": 1,
      "model_prob": 0.3333333333333333,
      "edge": 0.3133333333333333,
      "entered_at": "2026-03-21 19:51:11",
      "result": "loss",
      "pnl": -0.01,
      "resolved_at": "2026-03-22 13:10:07",
      "platform": "kalshi",
      "description": "Will the maximum temperature be  <46\u00b0 on Mar 21, 2026?"
    },
    {
      "id": 75,
      "ticker": "KXLOWTDEN-26MAR21-B50.5",
      "side": "yes",
      "entry_price": 0.01,
      "contracts": 1,
      "model_prob": 0.3333333333333333,
      "edge": 0.3133333333333333,
      "entered_at": "2026-03-21 19:51:11",
      "result": "loss",
      "pnl": -0.01,
      "resolved_at": "2026-03-22 13:09:35",
      "platform": "kalshi",
      "description": "Will the minimum temperature be  50-51\u00b0 on Mar 21, 2026?"
    },
    {
      "id": 76,
      "ticker": "KXLOWTLAX-26MAR21-B61.5",
      "side": "yes",
      "entry_price": 0.01,
      "contracts": 1,
      "model_prob": 0.3333333333333333,
      "edge": 0.3133333333333333,
      "entered_at": "2026-03-21 19:51:11",
      "result": "loss",
      "pnl": -0.01,
      "resolved_at": "2026-03-22 18:34:43",
      "platform": "kalshi",
      "description": "Will the minimum temperature be  61-62\u00b0 on Mar 21, 2026?"
    },
    {
      "id": 77,
      "ticker": "KXLOWTAUS-26MAR21-B57.5",
      "side": "yes",
      "entry_price": 0.01,
      "contracts": 1,
      "model_prob": 0.3333333333333333,
      "edge": 0.3133333333333333,
      "entered_at": "2026-03-21 19:51:11",
      "result": "loss",
      "pnl": -0.01,
      "resolved_at": "2026-03-22 13:09:46",
      "platform": "kalshi",
      "description": "Will the minimum temperature be  57-58\u00b0 on Mar 21, 2026?"
    },
    {
      "id": 78,
      "ticker": "KXHIGHTSFO-26MAR21-B72.5",
      "side": "yes",
      "entry_price": 0.01,
      "contracts": 1,
      "model_prob": 0.3333333333333333,
      "edge": 0.3133333333333333,
      "entered_at": "2026-03-21 19:51:11",
      "result": "loss",
      "pnl": -0.01,
      "resolved_at": "2026-03-22 13:10:16",
      "platform": "kalshi",
      "description": "Will the maximum temperature be  72-73\u00b0 on Mar 21, 2026?"
    },
    {
      "id": 61,
      "ticker": "KXHIGHTMIN-26MAR21-B72.5",
      "side": "yes",
      "entry_price": 0.01,
      "contracts": 1,
      "model_prob": 0.2,
      "edge": 0.18,
      "entered_at": "2026-03-21 19:46:05",
      "result": "loss",
      "pnl": -0.01,
      "resolved_at": "2026-03-22 13:09:55",
      "platform": "kalshi",
      "description": "Will the maximum temperature be  72-73\u00b0 on Mar 21, 2026?"
    },
    {
      "id": 62,
      "ticker": "KXLOWTMIA-26MAR21-B59.5",
      "side": "yes",
      "entry_price": 0.01,
      "contracts": 1,
      "model_prob": 0.1952662721893491,
      "edge": 0.1752662721893491,
      "entered_at": "2026-03-21 19:46:05",
      "result": "loss",
      "pnl": -0.01,
      "resolved_at": "2026-03-22 18:34:41",
      "platform": "kalshi",
      "description": "Will the minimum temperature be  59-60\u00b0 on Mar 21, 2026?"
    },
    {
      "id": 65,
      "ticker": "KXHIGHTMIN-26MAR21-B74.5",
      "side": "yes",
      "entry_price": 0.01,
      "contracts": 1,
      "model_prob": 0.19090909090909092,
      "edge": 0.1709090909090909,
      "entered_at": "2026-03-21 19:46:05",
      "result": "loss",
      "pnl": -0.01,
      "resolved_at": "2026-03-22 13:09:55",
      "platform": "kalshi",
      "description": "Will the maximum temperature be  74-75\u00b0 on Mar 21, 2026?"
    },
    {
      "id": 66,
      "ticker": "KXHIGHTBOS-26MAR21-B50.5",
      "side": "yes",
      "entry_price": 0.01,
      "contracts": 1,
      "model_prob": 0.18705035971223022,
      "edge": 0.1670503597122302,
      "entered_at": "2026-03-21 19:46:05",
      "result": "loss",
      "pnl": -0.01,
      "resolved_at": "2026-03-22 13:09:42",
      "platform": "kalshi",
      "description": "Will the maximum temperature be  50-51\u00b0 on Mar 21, 2026?"
    },
    {
      "id": 67,
      "ticker": "KXHIGHTMIN-26MAR21-B74.5",
      "side": "yes",
      "entry_price": 0.01,
      "contracts": 1,
      "model_prob": 0.18705035971223022,
      "edge": 0.1670503597122302,
      "entered_at": "2026-03-21 19:46:05",
      "result": "loss",
      "pnl": -0.01,
      "resolved_at": "2026-03-22 13:09:55",
      "platform": "kalshi",
      "description": "Will the maximum temperature be  74-75\u00b0 on Mar 21, 2026?"
    },
    {
      "id": 51,
      "ticker": "KXHIGHTATL-26MAR21-B82.5",
      "side": "yes",
      "entry_price": 0.01,
      "contracts": 1,
      "model_prob": 0.6666666666666666,
      "edge": 0.6466666666666666,
      "entered_at": "2026-03-21 19:45:08",
      "result": "loss",
      "pnl": -0.01,
      "resolved_at": "2026-03-22 13:10:03",
      "platform": "kalshi",
      "description": "Will the maximum temperature be  82-83\u00b0 on Mar 21, 2026?"
    },
    {
      "id": 53,
      "ticker": "KXHIGHTDC-26MAR21-B65.5",
      "side": "yes",
      "entry_price": 0.01,
      "contracts": 1,
      "model_prob": 0.3333333333333333,
      "edge": 0.3133333333333333,
      "entered_at": "2026-03-21 19:45:08",
      "result": "loss",
      "pnl": -0.01,
      "resolved_at": "2026-03-22 13:09:52",
      "platform": "kalshi",
      "description": "Will the maximum temperature be  65-66\u00b0 on Mar 21, 2026?"
    },
    {
      "id": 54,
      "ticker": "KXHIGHTSFO-26MAR21-B68.5",
      "side": "yes",
      "entry_price": 0.01,
      "contracts": 1,
      "model_prob": 0.3333333333333333,
      "edge": 0.3133333333333333,
      "entered_at": "2026-03-21 19:45:08",
      "result": "loss",
      "pnl": -0.01,
      "resolved_at": "2026-03-22 13:10:17",
      "platform": "kalshi",
      "description": "Will the maximum temperature be  68-69\u00b0 on Mar 21, 2026?"
    },
    {
      "id": 55,
      "ticker": "KXHIGHCHI-26MAR21-B67.5",
      "side": "yes",
      "entry_price": 0.01,
      "contracts": 1,
      "model_prob": 0.3333333333333333,
      "edge": 0.3133333333333333,
      "entered_at": "2026-03-21 19:45:08",
      "result": "loss",
      "pnl": -0.01,
      "resolved_at": "2026-03-22 13:09:48",
      "platform": "kalshi",
      "description": "Will the high temp in Chicago be 67-68\u00b0 on Mar 21, 2026?"
    },
    {
      "id": 58,
      "ticker": "KXLOWTAUS-26MAR21-B59.5",
      "side": "yes",
      "entry_price": 0.01,
      "contracts": 1,
      "model_prob": 0.2158273381294964,
      "edge": 0.19582733812949638,
      "entered_at": "2026-03-21 19:45:08",
      "result": "loss",
      "pnl": -0.01,
      "resolved_at": "2026-03-22 13:09:45",
      "platform": "kalshi",
      "description": "Will the minimum temperature be  59-60\u00b0 on Mar 21, 2026?"
    },
    {
      "id": 60,
      "ticker": "KXLOWTCHI-26MAR21-B39.5",
      "side": "yes",
      "entry_price": 0.01,
      "contracts": 1,
      "model_prob": 0.20863309352517986,
      "edge": 0.18863309352517985,
      "entered_at": "2026-03-21 19:45:08",
      "result": "loss",
      "pnl": -0.01,
      "resolved_at": "2026-03-22 13:09:30",
      "platform": "kalshi",
      "description": "Will the minimum temperature be  39-40\u00b0 on Mar 21, 2026?"
    },
    {
      "id": 41,
      "ticker": "KXHIGHTMIN-26MAR21-T72",
      "side": "yes",
      "entry_price": 0.01,
      "contracts": 1,
      "model_prob": 0.3333333333333333,
      "edge": 0.3133333333333333,
      "entered_at": "2026-03-21 19:40:42",
      "result": "loss",
      "pnl": -0.01,
      "resolved_at": "2026-03-22 13:09:53",
      "platform": "kalshi",
      "description": "Will the maximum temperature be  <72\u00b0 on Mar 21, 2026?"
    },
    {
      "id": 49,
      "ticker": "KXHIGHNY-26MAR21-B55.5",
      "side": "yes",
      "entry_price": 0.01,
      "contracts": 1,
      "model_prob": 0.22302158273381295,
      "edge": 0.20302158273381293,
      "entered_at": "2026-03-21 19:40:42",
      "result": "loss",
      "pnl": -0.01,
      "resolved_at": "2026-03-22 13:09:28",
      "platform": "kalshi",
      "description": "Will the **high temp in NYC** be 55-56\u00b0 on Mar 21, 2026?"
    },
    {
      "id": 50,
      "ticker": "KXHIGHNY-26MAR21-B55.5",
      "side": "yes",
      "entry_price": 0.01,
      "contracts": 1,
      "model_prob": 0.21893491124260356,
      "edge": 0.19893491124260354,
      "entered_at": "2026-03-21 19:40:42",
      "result": "loss",
      "pnl": -0.01,
      "resolved_at": "2026-03-22 13:09:28",
      "platform": "kalshi",
      "description": "Will the **high temp in NYC** be 55-56\u00b0 on Mar 21, 2026?"
    },
    {
      "id": 31,
      "ticker": "KXLOWTNYC-26MAR21-B41.5",
      "side": "yes",
      "entry_price": 0.05,
      "contracts": 1,
      "model_prob": 0.3333333333333333,
      "edge": 0.2733333333333333,
      "entered_at": "2026-03-21 19:35:39",
      "result": "loss",
      "pnl": -0.05,
      "resolved_at": "2026-03-22 13:10:02",
      "platform": "kalshi",
      "description": "Will the minimum temperature be  41-42\u00b0 on Mar 21, 2026?"
    },
    {
      "id": 36,
      "ticker": "KXHIGHTATL-26MAR21-T80",
      "side": "yes",
      "entry_price": 0.01,
      "contracts": 1,
      "model_prob": 0.26627218934911245,
      "edge": 0.24627218934911244,
      "entered_at": "2026-03-21 19:35:39",
      "result": "loss",
      "pnl": -0.01,
      "resolved_at": "2026-03-22 13:10:02",
      "platform": "kalshi",
      "description": "Will the maximum temperature be  <80\u00b0 on Mar 21, 2026?"
    },
    {
      "id": 37,
      "ticker": "KXLOWTMIA-26MAR21-T57",
      "side": "yes",
      "entry_price": 0.01,
      "contracts": 1,
      "model_prob": 0.26627218934911245,
      "edge": 0.24627218934911244,
      "entered_at": "2026-03-21 19:35:39",
      "result": "loss",
      "pnl": -0.01,
      "resolved_at": "2026-03-22 18:34:41",
      "platform": "kalshi",
      "description": "Will the minimum temperature be  <57\u00b0 on Mar 21, 2026?"
    },
    {
      "id": 38,
      "ticker": "KXHIGHMIA-26MAR21-B77.5",
      "side": "yes",
      "entry_price": 0.01,
      "contracts": 1,
      "model_prob": 0.26618705035971224,
      "edge": 0.24618705035971222,
      "entered_at": "2026-03-21 19:35:39",
      "result": "loss",
      "pnl": -0.01,
      "resolved_at": "2026-03-22 13:09:50",
      "platform": "kalshi",
      "description": "Will the **high temp in Miami** be 77-78\u00b0 on Mar 21, 2026?"
    },
    {
      "id": 39,
      "ticker": "KXHIGHTATL-26MAR21-T80",
      "side": "yes",
      "entry_price": 0.01,
      "contracts": 1,
      "model_prob": 0.2517985611510791,
      "edge": 0.2317985611510791,
      "entered_at": "2026-03-21 19:35:39",
      "result": "loss",
      "pnl": -0.01,
      "resolved_at": "2026-03-22 13:10:02",
      "platform": "kalshi",
      "description": "Will the maximum temperature be  <80\u00b0 on Mar 21, 2026?"
    },
    {
      "id": 23,
      "ticker": "KXHIGHNY-26MAR21-T53",
      "side": "yes",
      "entry_price": 0.01,
      "contracts": 1,
      "model_prob": 0.3333333333333333,
      "edge": 0.3133333333333333,
      "entered_at": "2026-03-21 19:31:10",
      "result": "loss",
      "pnl": -0.01,
      "resolved_at": "2026-03-22 13:09:27",
      "platform": "kalshi",
      "description": "Will the **high temp in NYC** be <53\u00b0 on Mar 21, 2026?"
    },
    {
      "id": 24,
      "ticker": "KXHIGHTATL-26MAR21-B80.5",
      "side": "yes",
      "entry_price": 0.01,
      "contracts": 1,
      "model_prob": 0.33093525179856115,
      "edge": 0.31093525179856113,
      "entered_at": "2026-03-21 19:31:10",
      "result": "loss",
      "pnl": -0.01,
      "resolved_at": "2026-03-22 13:10:04",
      "platform": "kalshi",
      "description": "Will the maximum temperature be  80-81\u00b0 on Mar 21, 2026?"
    },
    {
      "id": 26,
      "ticker": "KXHIGHTATL-26MAR21-B80.5",
      "side": "yes",
      "entry_price": 0.01,
      "contracts": 1,
      "model_prob": 0.3237410071942446,
      "edge": 0.30374100719424457,
      "entered_at": "2026-03-21 19:31:10",
      "result": "loss",
      "pnl": -0.01,
      "resolved_at": "2026-03-22 13:10:04",
      "platform": "kalshi",
      "description": "Will the maximum temperature be  80-81\u00b0 on Mar 21, 2026?"
    },
    {
      "id": 27,
      "ticker": "KXHIGHTDAL-26MAR21-T90",
      "side": "yes",
      "entry_price": 0.01,
      "contracts": 1,
      "model_prob": 0.30935251798561153,
      "edge": 0.2893525179856115,
      "entered_at": "2026-03-21 19:31:10",
      "result": "loss",
      "pnl": -0.01,
      "resolved_at": "2026-03-22 13:09:43",
      "platform": "kalshi",
      "description": "Will the maximum temperature be  <90\u00b0 on Mar 21, 2026?"
    },
    {
      "id": 28,
      "ticker": "KXLOWTDEN-26MAR21-T53",
      "side": "yes",
      "entry_price": 0.01,
      "contracts": 1,
      "model_prob": 0.302158273381295,
      "edge": 0.28215827338129496,
      "entered_at": "2026-03-21 19:31:10",
      "result": "loss",
      "pnl": -0.01,
      "resolved_at": "2026-03-22 13:09:34",
      "platform": "kalshi",
      "description": "Will the minimum temperature be  >53\u00b0 on Mar 21, 2026?"
    },
    {
      "id": 30,
      "ticker": "KXLOWTNYC-26MAR21-B43.5",
      "side": "yes",
      "entry_price": 0.05,
      "contracts": 1,
      "model_prob": 0.3333333333333333,
      "edge": 0.2733333333333333,
      "entered_at": "2026-03-21 19:31:10",
      "result": "loss",
      "pnl": -0.05,
      "resolved_at": "2026-03-22 13:10:01",
      "platform": "kalshi",
      "description": "Will the minimum temperature be  43-44\u00b0 on Mar 21, 2026?"
    },
    {
      "id": 16,
      "ticker": "KXLOWTMIA-26MAR21-T64",
      "side": "yes",
      "entry_price": 0.01,
      "contracts": 1,
      "model_prob": 0.3597122302158273,
      "edge": 0.3397122302158273,
      "entered_at": "2026-03-21 19:27:21",
      "result": "loss",
      "pnl": -0.01,
      "resolved_at": "2026-03-22 18:34:40",
      "platform": "kalshi",
      "description": "Will the minimum temperature be  >64\u00b0 on Mar 21, 2026?"
    },
    {
      "id": 17,
      "ticker": "KXHIGHLAX-26MAR21-T83",
      "side": "yes",
      "entry_price": 0.01,
      "contracts": 1,
      "model_prob": 0.3597122302158273,
      "edge": 0.3397122302158273,
      "entered_at": "2026-03-21 19:27:21",
      "result": "loss",
      "pnl": -0.01,
      "resolved_at": "2026-03-22 13:10:09",
      "platform": "kalshi",
      "description": "Will the **high temp in LA** be >83\u00b0 on Mar 21, 2026?"
    },
    {
      "id": 18,
      "ticker": "KXHIGHDEN-26MAR21-T86",
      "side": "yes",
      "entry_price": 0.03,
      "contracts": 1,
      "model_prob": 0.3597122302158273,
      "edge": 0.3197122302158273,
      "entered_at": "2026-03-21 19:27:21",
      "result": "loss",
      "pnl": -0.03,
      "resolved_at": "2026-03-22 11:09:59",
      "platform": "kalshi",
      "description": "Will the **high temp in Denver** be <86\u00b0 on Mar 21, 2026?"
    },
    {
      "id": 19,
      "ticker": "KXHIGHDEN-26MAR21-T86",
      "side": "yes",
      "entry_price": 0.04,
      "contracts": 1,
      "model_prob": 0.3669064748201439,
      "edge": 0.3169064748201439,
      "entered_at": "2026-03-21 19:27:21",
      "result": "loss",
      "pnl": -0.04,
      "resolved_at": "2026-03-22 11:09:59",
      "platform": "kalshi",
      "description": "Will the **high temp in Denver** be <86\u00b0 on Mar 21, 2026?"
    },
    {
      "id": 20,
      "ticker": "KXHIGHTPHX-26MAR21-T103",
      "side": "yes",
      "entry_price": 0.04,
      "contracts": 1,
      "model_prob": 0.3669064748201439,
      "edge": 0.3169064748201439,
      "entered_at": "2026-03-21 19:27:21",
      "result": "loss",
      "pnl": -0.04,
      "resolved_at": "2026-03-22 13:10:14",
      "platform": "kalshi",
      "description": "Will the maximum temperature be  <103\u00b0 on Mar 21, 2026?"
    },
    {
      "id": 1,
      "ticker": "KXRAINNYC-26MAR21-T0",
      "side": "yes",
      "entry_price": 0.01,
      "contracts": 1,
      "model_prob": 1.0,
      "edge": 0.98,
      "entered_at": "2026-03-21 18:23:32",
      "result": "loss",
      "pnl": -0.01,
      "resolved_at": "2026-03-22 13:09:24",
      "platform": "kalshi",
      "description": "Will it **rain** in New York City on Saturday?"
    },
    {
      "id": 2,
      "ticker": "KXLOWTAUS-26MAR21-T60",
      "side": "yes",
      "entry_price": 0.01,
      "contracts": 1,
      "model_prob": 0.7841726618705036,
      "edge": 0.7641726618705036,
      "entered_at": "2026-03-21 18:23:32",
      "result": "loss",
      "pnl": -0.01,
      "resolved_at": "2026-03-22 13:09:45",
      "platform": "kalshi",
      "description": "Will the minimum temperature be  >60\u00b0 on Mar 21, 2026?"
    },
    {
      "id": 5,
      "ticker": "KXHIGHTBOS-26MAR21-T50",
      "side": "yes",
      "entry_price": 0.01,
      "contracts": 1,
      "model_prob": 0.5539568345323741,
      "edge": 0.5339568345323741,
      "entered_at": "2026-03-21 18:23:32",
      "result": "loss",
      "pnl": -0.01,
      "resolved_at": "2026-03-22 13:09:40",
      "platform": "kalshi",
      "description": "Will the maximum temperature be  <50\u00b0 on Mar 21, 2026?"
    },
    {
      "id": 7,
      "ticker": "KXHIGHAUS-26MAR21-T91",
      "side": "yes",
      "entry_price": 0.12,
      "contracts": 1,
      "model_prob": 0.6115107913669064,
      "edge": 0.48151079136690644,
      "entered_at": "2026-03-21 18:23:32",
      "result": "loss",
      "pnl": -0.12,
      "resolved_at": "2026-03-22 13:09:56",
      "platform": "kalshi",
      "description": "Will the **high temp in Austin** be <91\u00b0 on Mar 21, 2026?"
    },
    {
      "id": 9,
      "ticker": "KXLOWTLAX-26MAR21-T62",
      "side": "yes",
      "entry_price": 0.01,
      "contracts": 1,
      "model_prob": 0.48201438848920863,
      "edge": 0.4620143884892086,
      "entered_at": "2026-03-21 18:23:32",
      "result": "loss",
      "pnl": -0.01,
      "resolved_at": "2026-03-22 18:34:42",
      "platform": "kalshi",
      "description": "Will the minimum temperature be  >62\u00b0 on Mar 21, 2026?"
    },
    {
      "id": 10,
      "ticker": "KXHIGHTSFO-26MAR21-T66",
      "side": "yes",
      "entry_price": 0.01,
      "contracts": 1,
      "model_prob": 0.4244604316546763,
      "edge": 0.40446043165467627,
      "entered_at": "2026-03-21 18:23:32",
      "result": "loss",
      "pnl": -0.01,
      "resolved_at": "2026-03-22 13:10:16",
      "platform": "kalshi",
      "description": "Will the maximum temperature be  <66\u00b0 on Mar 21, 2026?"
    }
  ],
  "positions": [
    {
      "id": 9,
      "ticker": "will-nyc-have-between-3-and-4-inches-of-precipitation-in-march",
      "side": "yes",
      "entry_price": 0.185,
      "contracts": 50.0,
      "model_prob": 1.0,
      "edge": 0.815,
      "entered_at": "2026-03-22 20:55:38",
      "platform": "polymarket",
      "description": "Will NYC have between 3 and 4 inches of precipitation in March?"
    },
    {
      "id": 10,
      "ticker": "will-nyc-have-between-4-and-5-inches-of-precipitation-in-march",
      "side": "yes",
      "entry_price": 0.34,
      "contracts": 50.0,
      "model_prob": 1.0,
      "edge": 0.66,
      "entered_at": "2026-03-22 20:55:38",
      "platform": "polymarket",
      "description": "Will NYC have between 4 and 5 inches of precipitation in March?"
    },
    {
      "id": 11,
      "ticker": "will-nyc-have-between-5-and-6-inches-of-precipitation-in-march",
      "side": "no",
      "entry_price": 0.755,
      "contracts": 50.0,
      "model_prob": 0.1329,
      "edge": 0.1121,
      "entered_at": "2026-03-22 20:55:38",
      "platform": "polymarket",
      "description": "Will NYC have between 5 and 6 inches of precipitation in March?"
    },
    {
      "id": 12,
      "ticker": "will-seattle-have-between-4-and-5-inches-of-precipitation-in-march",
      "side": "yes",
      "entry_price": 0.177,
      "contracts": 50.0,
      "model_prob": 1.0,
      "edge": 0.823,
      "entered_at": "2026-03-22 20:55:38",
      "platform": "polymarket",
      "description": "Will Seattle have between 4 and 5 inches of precipitation in March?"
    },
    {
      "id": 13,
      "ticker": "will-seattle-have-between-5-and-6-inches-of-precipitation-in-march",
      "side": "yes",
      "entry_price": 0.7145,
      "contracts": 50.0,
      "model_prob": 1.0,
      "edge": 0.2855,
      "entered_at": "2026-03-22 20:55:38",
      "platform": "polymarket",
      "description": "Will Seattle have between 5 and 6 inches of precipitation in March?"
    },
    {
      "id": 14,
      "ticker": "will-seattle-have-between-6-and-7-inches-of-precipitation-in-march",
      "side": "yes",
      "entry_price": 0.0415,
      "contracts": 50.0,
      "model_prob": 1.0,
      "edge": 0.9585,
      "entered_at": "2026-03-22 20:55:38",
      "platform": "polymarket",
      "description": "Will Seattle have between 6 and 7 inches of precipitation in March?"
    }
  ],
  "pipeline_health": {
    "last_pipeline_run": "2026-03-22 20:54:50",
    "watcher_status": "unknown",
    "kalshi_markets": 562,
    "polymarket_markets": 475,
    "total_markets": 1037,
    "cross_platform_opportunities": 9,
    "model_prices_total": 12742,
    "cities_active": 19,
    "avg_model_confidence": 0.178
  },
  "experiments": [
    {
      "experiment_id": "baseline",
      "timestamp": "2026-03-22T13:11:31.571719",
      "description": "exp_6dc9b955",
      "hypothesis": "(from previous cycle)",
      "params_changed": "(see previous log)",
      "paper_pnl": "0.59",
      "brier_score": "0.2266",
      "win_rate": "0.0781",
      "edge_accuracy": "-0.2690",
      "composite_score": "-0.6594",
      "kept": "False",
      "git_sha": "ae7a0d9"
    },
    {
      "experiment_id": "baseline",
      "timestamp": "2026-03-22T11:11:35.651560",
      "description": "Initial baseline",
      "hypothesis": "Establish baseline metrics",
      "params_changed": "none",
      "paper_pnl": "0.68",
      "brier_score": "0.3216",
      "win_rate": "0.3333",
      "edge_accuracy": "0.0000",
      "composite_score": "7.1422",
      "kept": "True",
      "git_sha": "ae7a0d9"
    }
  ],
  "alerts": [],
  "exported_at": "2026-03-22T20:57:02.316986+00:00"
}